dtperiod.py
setup.py
dtperiod.egg-info/PKG-INFO
dtperiod.egg-info/SOURCES.txt
dtperiod.egg-info/dependency_links.txt
dtperiod.egg-info/top_level.txt